__init__.py
cafe_data_calculator/calculator.py
cafe_data_calculator-0.0.2.dist-info/METADATA
cafe_data_calculator-0.0.2.dist-info/WHEEL
cafe_data_calculator-0.0.2.dist-info/top_level.txt
cafe_data_calculator-0.0.2.dist-info/RECORD
