Metadata-Version: 2.1
Name: cafe-data-calculator
Version: 0.0.2
Summary: Created for cafe and data talk 
Author-email: Eduardo Zevallos <EduardoLZevallos@gmail.com>
Requires-Python: >=3.8
